RachitRobotarium/__init__.py
RachitRobotarium/utils.py
RachitRobotarium-0.0.1.dist-info/LICENSE
RachitRobotarium-0.0.1.dist-info/METADATA
RachitRobotarium-0.0.1.dist-info/WHEEL
RachitRobotarium-0.0.1.dist-info/top_level.txt
RachitRobotarium-0.0.1.dist-info/RECORD
